apptrail_application_events_sdk/__init__.py
apptrail_application_events_sdk/_client.py
apptrail_application_events_sdk/py.typed
apptrail_application_events_sdk/raw-event-schema.json
apptrail_application_events_sdk-0.0.3.dist-info/METADATA
apptrail_application_events_sdk-0.0.3.dist-info/WHEEL
apptrail_application_events_sdk-0.0.3.dist-info/top_level.txt
apptrail_application_events_sdk-0.0.3.dist-info/RECORD
