Metadata-Version: 2.1
Name: apptrail-application-events-sdk
Version: 0.0.3
Summary: Apptrail Application Events SDK for Python
Home-page: https://apptrail.com
Author: Apptrail Team
Author-email: support@apptrail.com
License: MIT
Project-URL: SDK Reference, https://apptrail.com/docs/applications/guide/working-with-events/using-the-events-sdk/application-events-sdk-python
Project-URL: Developer Guide, https://apptrail.com/docs/applications/guide
Project-URL: Apptrail Docs, https://apptrail.com/docs
Keywords: apptrail,apptrail events SDK,audit logs,audit trails,apptrail application events SDK
Platform: UNKNOWN
Classifier: Programming Language :: Python :: 3
Classifier: License :: OSI Approved :: Apache Software License
Classifier: Operating System :: OS Independent
Classifier: Topic :: System :: Logging
Classifier: Topic :: Security
Requires-Python: >=3.6
Requires-Dist: requests
Requires-Dist: backoff
Requires-Dist: jsonschema[format_nongpl]
Requires-Dist: jsonlines
